talktosql/__init__.py
talktosql/requirements.txt
talktosql/talktosql.py
talktosql-0.0.1.dist-info/METADATA
talktosql-0.0.1.dist-info/WHEEL
talktosql-0.0.1.dist-info/entry_points.txt
talktosql-0.0.1.dist-info/licenses/LICENSE
talktosql-0.0.1.dist-info/RECORD
