Metadata-Version: 2.1
Name: talktosql
Version: 0.0.1
Summary: Query your DB using natural language instead of SQL queries
Project-URL: Homepage, https://github.com/woniesong92/talktosql
Project-URL: Bug Tracker, https://github.com/woniesong92/talktosql/issues
Author-email: woniesong92 <woniesong92@gmail.com>
License-File: LICENSE
Classifier: License :: OSI Approved :: MIT License
Classifier: Operating System :: OS Independent
Classifier: Programming Language :: Python :: 3
Requires-Python: >=3.7
Requires-Dist: aiohttp==3.8.4
Requires-Dist: aiosignal==1.3.1
Requires-Dist: async-timeout==4.0.2
Requires-Dist: attrs==22.2.0
Requires-Dist: certifi==2022.12.7
Requires-Dist: charset-normalizer==3.1.0
Requires-Dist: frozenlist==1.3.3
Requires-Dist: greenlet==2.0.2
Requires-Dist: idna==3.4
Requires-Dist: multidict==6.0.4
Requires-Dist: mysqlclient==2.1.1
Requires-Dist: openai==0.27.2
Requires-Dist: prettytable==3.6.0
Requires-Dist: psycopg2==2.9.5
Requires-Dist: python-dotenv==1.0.0
Requires-Dist: requests==2.28.2
Requires-Dist: sqlalchemy==2.0.7
Requires-Dist: termcolor==2.2.0
Requires-Dist: tqdm==4.65.0
Requires-Dist: typing-extensions==4.5.0
Requires-Dist: urllib3==1.26.15
Requires-Dist: wcwidth==0.2.6
Requires-Dist: yarl==1.8.2
